fast_create.py
temp/.env
temp/Dockerfile
temp/__init__.py
temp/app.py
temp/database.py
temp/hashing.py
temp/imports.py
temp/main.py
temp/middleware.py
temp/requirements.txt
temp/test.py
temp/__pycache__/__init__.cpython-312.pyc
temp/__pycache__/app.cpython-312.pyc
temp/__pycache__/database.cpython-312.pyc
temp/__pycache__/hashing.cpython-312.pyc
temp/__pycache__/imports.cpython-312.pyc
temp/__pycache__/main.cpython-312.pyc
temp/models/UserModel.py
temp/models/__init__.py
temp/models/__pycache__/UserModel.cpython-312.pyc
temp/models/__pycache__/__init__.cpython-312.pyc
temp/routers/__init__.py
temp/routers/profile.py
temp/routers/__pycache__/__init__.cpython-312.pyc
temp/routers/__pycache__/profile.cpython-312.pyc
temp/schemas/__init__.py
temp/schemas/userSchema.py
temp/schemas/__pycache__/__init__.cpython-312.pyc
temp/schemas/__pycache__/userSchema.cpython-312.pyc
temp/securities/__init__.py
temp/securities/auth_token.py
temp/securities/authentication.py
temp/securities/logs.py
temp/securities/oauth2.py
temp/securities/test_auth.py
temp/securities/tokenSchema.py
temp/securities/verifiy.py
temp/securities/__pycache__/__init__.cpython-312.pyc
temp/securities/__pycache__/auth_token.cpython-312.pyc
temp/securities/__pycache__/authentication.cpython-312.pyc
temp/securities/__pycache__/logs.cpython-312.pyc
temp/securities/__pycache__/oauth2.cpython-312.pyc
temp/securities/__pycache__/test_auth.cpython-312-pytest-8.3.5.pyc
temp/securities/__pycache__/tokenSchema.cpython-312.pyc
temp/utilities/__init__.py
temp/utilities/mail.py
temp/utilities/__pycache__/__init__.cpython-312.pyc
temp/utilities/__pycache__/mail.cpython-312.pyc
fast_create-0.2.2.dist-info/METADATA
fast_create-0.2.2.dist-info/WHEEL
fast_create-0.2.2.dist-info/entry_points.txt
fast_create-0.2.2.dist-info/top_level.txt
fast_create-0.2.2.dist-info/RECORD
