Metadata-Version: 2.4
Name: fast-create
Version: 0.2.2
Summary: A CLI tool to quickly generate FastAPI project structures
Author-email: Joseph Chukwuma Christopher <joechristophersc@email.com>
License: MIT
Requires-Python: >=3.7
Requires-Dist: fastapi[all]
Requires-Dist: uvicorn
Requires-Dist: alembic
Requires-Dist: python-dotenv
Requires-Dist: psycopg2-binary
Requires-Dist: sqlmodel
Requires-Dist: fastapi_mail
Requires-Dist: pydantic
Requires-Dist: python-jose[cryptography]
Requires-Dist: oauth2
Requires-Dist: passlib
Requires-Dist: sqlalchemy
